langchain_nimble/__init__.py
langchain_nimble/_types.py
langchain_nimble/_utilities.py
langchain_nimble/extract_tool.py
langchain_nimble/py.typed
langchain_nimble/retrievers.py
langchain_nimble/search_tool.py
langchain_nimble-2.1.0.dist-info/METADATA
langchain_nimble-2.1.0.dist-info/WHEEL
langchain_nimble-2.1.0.dist-info/licenses/LICENSE
langchain_nimble-2.1.0.dist-info/RECORD
