Metadata-Version: 2.4
Name: langchain-nimble
Version: 2.1.0
Summary: An integration package connecting Nimble and LangChain
Project-URL: Homepage, https://www.nimbleway.com
Project-URL: Documentation, https://docs.langchain.com/oss/python/integrations/providers/nimble
Project-URL: Source, https://github.com/Nimbleway/langchain-nimble
Project-URL: Repository, https://github.com/Nimbleway/langchain-nimble
Project-URL: Release Notes, https://github.com/Nimbleway/langchain-nimble/releases
Project-URL: Twitter, https://x.com/LangChainAI
Project-URL: Slack, https://www.langchain.com/join-community
Project-URL: Reddit, https://www.reddit.com/r/LangChain/
License: MIT
License-File: LICENSE
Requires-Python: <4.0.0,>=3.10.0
Requires-Dist: httpx<1.0.0,>=0.28.1
Requires-Dist: langchain-core<2.0.0,>=1.0.0
